{
  "kind": "coverage_report",
  "version": "1.0",
  "generatedAt": "2026-02-26T20:41:30.316Z",
  "sources": {
    "buildRequest": true,
    "implementationPlan": true
  },
  "requirements": {
    "total": 2,
    "implemented": 2,
    "items": [
      {
        "id": "REQ-29",
        "summary": "Save the uploaded VOXA logo image (white abstract V-shaped mark with purple shadow on black background) as a static asset at frontend/public/assets/generated/voxa-logo.png and render it in the Hero section (HeroSection.tsx) in place of the current SVG sound-wave icon, displayed at an appropriate size (e.g., 64×64 px) next to the 'VOXA' wordmark.",
        "status": "implemented",
        "plannedFiles": [
          "frontend/public/assets/generated/voxa-logo.dim_256x256.png",
          "frontend/src/components/HeroSection.tsx"
        ],
        "matchedFiles": [
          "frontend/public/assets/generated/voxa-logo.dim_256x256.png",
          "frontend/src/components/HeroSection.tsx"
        ]
      },
      {
        "id": "REQ-30",
        "summary": "Also display the VOXA logo image (voxa-logo.png) in the sticky Navigation bar alongside the 'VOXA' brand name, replacing any existing SVG icon used there, at a small size appropriate for a navbar (e.g., 32×32 px).",
        "status": "implemented",
        "plannedFiles": [
          "frontend/src/components/Navigation.tsx"
        ],
        "matchedFiles": [
          "frontend/src/components/Navigation.tsx"
        ]
      }
    ]
  },
  "changedFiles": [
    "build-request.json",
    "feature_evidence.json",
    "frontend-file-summaries.txt",
    "frontend-implementation-plan.json",
    "frontend/public/assets/generated/voxa-logo.dim_256x256.png",
    "frontend/src/components/HeroSection.tsx",
    "frontend/src/components/Navigation.tsx",
    "project_state.json",
    "scratch/component-selection.json",
    "spec.md",
    "spec_vs_diff_report.json"
  ]
}